WiresharkManual/README.md
WiresharkManual/__init__.py
WiresharkManual/__main__.py
WiresharkManual/file.epub
WiresharkManual/index.html
WiresharkManual/css/__init__.py
WiresharkManual/css/annotations.css
WiresharkManual/css/main.css
WiresharkManual/css/normalize.css
WiresharkManual/css/popup.css
WiresharkManual/font/__init__.py
WiresharkManual/font/fontello.eot
WiresharkManual/font/fontello.svg
WiresharkManual/font/fontello.ttf
WiresharkManual/font/fontello.woff
WiresharkManual/img/__init__.py
WiresharkManual/img/annotator-glyph-sprite.png
WiresharkManual/img/annotator-icon-sprite.png
WiresharkManual/img/apple-touch-icon.png
WiresharkManual/img/cancelfullscreen.png
WiresharkManual/img/close.png
WiresharkManual/img/fullscreen.png
WiresharkManual/img/loader.gif
WiresharkManual/img/menu-icon.png
WiresharkManual/img/save.png
WiresharkManual/img/saved.png
WiresharkManual/img/settings-s.png
WiresharkManual/img/settings.png
WiresharkManual/img/star.png
WiresharkManual/js/__init__.py
WiresharkManual/js/epub.js
WiresharkManual/js/epub.min.js
WiresharkManual/js/epub.min.map
WiresharkManual/js/hooks.min.js
WiresharkManual/js/hooks.min.map
WiresharkManual/js/reader.js
WiresharkManual/js/reader.js.map
WiresharkManual/js/reader.min.js
WiresharkManual/js/reader.min.map
WiresharkManual/js/hooks/__init__.py
WiresharkManual/js/hooks/extensions/__init__.py
WiresharkManual/js/hooks/extensions/highlight.js
WiresharkManual/js/libs/__init__.py
WiresharkManual/js/libs/jquery.min.js
WiresharkManual/js/libs/localforage.min.js
WiresharkManual/js/libs/screenfull.js
WiresharkManual/js/libs/screenfull.min.js
WiresharkManual/js/libs/zip.min.js
WiresharkManual/js/plugins/__init__.py
WiresharkManual/js/plugins/hypothesis.js
WiresharkManual/js/plugins/search.js
wireshark_manual-2024.3.2.0.dist-info/METADATA
wireshark_manual-2024.3.2.0.dist-info/WHEEL
wireshark_manual-2024.3.2.0.dist-info/entry_points.txt
wireshark_manual-2024.3.2.0.dist-info/top_level.txt
wireshark_manual-2024.3.2.0.dist-info/RECORD
